pynetworktables2js/__init__.py
pynetworktables2js/__main__.py
pynetworktables2js/aiohttp_handlers.py
pynetworktables2js/nt_serial.py
pynetworktables2js/tornado_handlers.py
pynetworktables2js/version.py
pynetworktables2js/js/camera.js
pynetworktables2js/js/jquery_ext.js
pynetworktables2js/js/networktables.js
pynetworktables2js/js/utils.js
pynetworktables2js-2021.0.1.dist-info/LICENSE
pynetworktables2js-2021.0.1.dist-info/METADATA
pynetworktables2js-2021.0.1.dist-info/WHEEL
pynetworktables2js-2021.0.1.dist-info/entry_points.txt
pynetworktables2js-2021.0.1.dist-info/top_level.txt
pynetworktables2js-2021.0.1.dist-info/RECORD
