Metadata-Version: 2.1
Name: pynetworktables2js
Version: 2021.0.1
Summary: Forwards NetworkTables traffic to a web page via a Websocket
Home-page: https://github.com/robotpy/pynetworktables2js
Author: RobotPy Development Team
Author-email: robotpy@googlegroups.com
License: BSD License
Keywords: frc first robotics networktables
Platform: UNKNOWN
Classifier: Development Status :: 5 - Production/Stable
Classifier: Intended Audience :: Developers
Classifier: Intended Audience :: Education
Classifier: License :: OSI Approved :: BSD License
Classifier: Operating System :: OS Independent
Classifier: Topic :: Scientific/Engineering
Requires-Dist: cbor2 (<5.0)
Requires-Dist: tornado
Requires-Dist: pynetworktables
